dnscli/__init__.py
dnscli/config.py
dnscli/version.py
dnscli/cli/__init__.py
dnscli/cli/cli.py
dnscli/cli/config.py
dnscli/cli/domain.py
dnscli/cli/record.py
dnscli/providers/__init__.py
dnscli/providers/aliyun.py
dnscli/providers/base.py
dnscli/providers/cloudflare.py
dnscli/providers/tencent.py
dnscli-0.1.4.dist-info/METADATA
dnscli-0.1.4.dist-info/WHEEL
dnscli-0.1.4.dist-info/entry_points.txt
dnscli-0.1.4.dist-info/licenses/LICENSE
dnscli-0.1.4.dist-info/RECORD
