Metadata-Version: 2.4
Name: dnscli
Version: 0.1.4
Summary: 一个用于管理多云DNS记录的命令行工具
Project-URL: Homepage, https://github.com/liwanggui/dnscli
Project-URL: Bug Reports, https://github.com/liwanggui/dnscli/issues
Project-URL: Source, https://github.com/liwanggui/dnscli
Author-email: liwanggui <liwanggui@163.com>
License: MIT
License-File: LICENSE
Keywords: aliyun,dns,dnscli,dnspod,tencent
Classifier: Development Status :: 3 - Alpha
Classifier: Intended Audience :: Developers
Classifier: License :: OSI Approved :: MIT License
Classifier: Programming Language :: Python :: 3
Classifier: Programming Language :: Python :: 3.6
Classifier: Programming Language :: Python :: 3.7
Classifier: Programming Language :: Python :: 3.8
Classifier: Programming Language :: Python :: 3.9
Classifier: Topic :: Internet :: Name Service (DNS)
Requires-Python: >=3.6
Requires-Dist: aliyun-python-sdk-alidns>=2.6.42
Requires-Dist: aliyun-python-sdk-core>=2.13.36
Requires-Dist: click>=8.0.0
Requires-Dist: cloudflare>=4.0.0
Requires-Dist: prettytable>=3.14.0
Requires-Dist: pyyaml>=6.0
Requires-Dist: tencentcloud-sdk-python>=3.0.0
